[
  {
    "__TYPE__": "SharedSliceContent",
    "variation": "default",
    "primary": {
      "title": {
        "__TYPE__": "StructuredTextContent",
        "value": [
          {
            "type": "heading1",
            "content": {
              "text": "Bottom"
            }
          }
        ]
      },
      "description": {
        "__TYPE__": "StructuredTextContent",
        "value": [
          {
            "type": "paragraph",
            "content": {
              "text": "Magna fugiat sint cillum aute ex."
            }
          }
        ]
      },
      "link": {
        "__TYPE__": "LinkContent",
        "value": {
          "__TYPE__": "ExternalLink",
          "url": "https://slicemachine.dev"
        }
      },
      "link_label": {
        "__TYPE__": "FieldContent",
        "value": "mud",
        "type": "Text"
      }
    },
    "items": [
      {
        "__TYPE__": "GroupItemContent",
        "value": []
      }
    ]
  }
]